jsn/__init__.py
jsn-1.3.4.dist-info/METADATA
jsn-1.3.4.dist-info/WHEEL
jsn-1.3.4.dist-info/top_level.txt
jsn-1.3.4.dist-info/RECORD
