Metadata-Version: 2.1
Name: jsn
Version: 1.3.4
Summary: A relaxed, user-friendly json-like data format.
Home-page: https://github.com/polymonster/jsn
Author: Alex Dixon
Author-email: alexandercdixon@gmail.com
Classifier: Programming Language :: Python :: 2
Classifier: Programming Language :: Python :: 3
Classifier: Development Status :: 4 - Beta
Classifier: License :: OSI Approved :: MIT License
Classifier: Operating System :: OS Independent
Requires-Python: >=2.6
